profile_t/__init__.py
profile_t/either.py
profile_t/plots.py
profile_t/symbolic_expression.py
profile_t-1.0.2.dist-info/LICENSE
profile_t-1.0.2.dist-info/METADATA
profile_t-1.0.2.dist-info/WHEEL
profile_t-1.0.2.dist-info/top_level.txt
profile_t-1.0.2.dist-info/RECORD
