Metadata-Version: 2.1
Name: profile-t
Version: 1.0.2
Summary: Profile t calculation and plots for regression model
Home-page: https://github.com/folivetti/profile_t
Author: Fabricio Olivetti de Franca, Gabriel Kronberger
Author-email: Fabricio Olivetti de Franca <folivetti@ufabc.edu.br>, Gabriel Kronberger <Gabriel.Kronberger@fh-hagenberg.at>
License: MIT License        
Project-URL: Homepage, https://github.com/folivetti/profile_t
Project-URL: Bug Tracker, https://github.com/folivetti/profile_t/issues
Classifier: Programming Language :: Python :: 3
Classifier: License :: OSI Approved :: MIT License
Classifier: Operating System :: OS Independent
Requires-Python: >=3.7
License-File: LICENSE
Requires-Dist: numpy (>=1.9.0)
Requires-Dist: scipy (>=1.9.0)
Requires-Dist: sympy (>=1.7.0)
Requires-Dist: matplotlib (>=2.0.0)
